fars_cleaner/__init__.py
fars_cleaner/builder.py
fars_cleaner/data_loader.py
fars_cleaner/datasets.py
fars_cleaner/extra_info.py
fars_cleaner/fars_processor.py
fars_cleaner/fars_utils.py
fars_cleaner/lookup_tables/Accident.xlsx
fars_cleaner/lookup_tables/Additional_Information.xlsx
fars_cleaner/lookup_tables/Parkwork.xlsx
fars_cleaner/lookup_tables/Person.xlsx
fars_cleaner/lookup_tables/Vehicle.xlsx
fars_cleaner/lookup_tables/Vehnit.xlsx
fars_cleaner/lookup_tables/mapping.dict
fars_cleaner/registry.txt
fars_cleaner-1.3.5.dist-info/LICENSE
fars_cleaner-1.3.5.dist-info/WHEEL
fars_cleaner-1.3.5.dist-info/METADATA
fars_cleaner-1.3.5.dist-info/RECORD
