Metadata-Version: 2.1
Name: fars-cleaner
Version: 1.3.5
Summary: A package for loading and preprocessing the NHTSA FARS crash database
Home-page: https://github.com/mzabrams/fars-cleaner
License: BSD-3-Clause
Keywords: FARS,crash analysis,data preprocessing,NHTSA,vehicle safety
Author: Mitchell Abrams
Author-email: mitchell.abrams@duke.edu
Maintainer: Mitchell Abrams
Maintainer-email: mitchell.abrams@duke.edu
Requires-Python: >=3.8,<4.0
Classifier: Development Status :: 5 - Production/Stable
Classifier: Intended Audience :: Science/Research
Classifier: License :: OSI Approved :: BSD License
Classifier: Operating System :: OS Independent
Classifier: Programming Language :: Python
Classifier: Programming Language :: Python :: 3
Classifier: Programming Language :: Python :: 3.8
Classifier: Programming Language :: Python :: 3.9
Classifier: Programming Language :: Python :: 3.10
Classifier: Programming Language :: Python :: 3.11
Classifier: Programming Language :: Python :: 3
Provides-Extra: dev
Requires-Dist: dask
Requires-Dist: distributed (>=2022,<2023)
Requires-Dist: hypothesis; extra == "dev"
Requires-Dist: numpy (>=1.22.0,<2.0.0); python_version >= "3.8"
Requires-Dist: pandas (>=1.4,<2.0); python_version >= "3.8"
Requires-Dist: pathlib
Requires-Dist: pooch (>=1.6.0)
Requires-Dist: pyjanitor (>=0.23.1,<0.24.0)
Requires-Dist: pytest (>=7.1.0,<8.0.0); extra == "dev"
Requires-Dist: requests
Requires-Dist: scipy (>=1.7.0,<2.0.0)
Requires-Dist: thefuzz
Requires-Dist: tqdm
Project-URL: Repository, https://github.com/mzabrams/fars-cleaner
